invenio_records_permissions/__init__.py
invenio_records_permissions/api.py
invenio_records_permissions/config.py
invenio_records_permissions/errors.py
invenio_records_permissions/ext.py
invenio_records_permissions/generators.py
invenio_records_permissions/policies/__init__.py
invenio_records_permissions/policies/base.py
invenio_records_permissions/policies/records.py
invenio_records_permissions-2.0.0.dist-info/licenses/AUTHORS.rst
invenio_records_permissions-2.0.0.dist-info/licenses/LICENSE
invenio_records_permissions-2.0.0.dist-info/METADATA
invenio_records_permissions-2.0.0.dist-info/WHEEL
invenio_records_permissions-2.0.0.dist-info/entry_points.txt
invenio_records_permissions-2.0.0.dist-info/top_level.txt
invenio_records_permissions-2.0.0.dist-info/RECORD
